{"nodes": [{"id": "home_ubuntu_github_qmath_scripts_setup_db_sh", "label": "setup-db.sh", "file_type": "code", "source_file": "scripts/setup-db.sh", "source_location": "L1", "metadata": {"language": "bash", "kind": "file"}}, {"id": "home_ubuntu_github_qmath_scripts_setup_db_sh__entry", "label": "setup-db.sh script", "file_type": "code", "source_file": "scripts/setup-db.sh", "source_location": "L1", "metadata": {"language": "bash", "kind": "bash_entrypoint"}}, {"id": "scripts_setup_db_check_docker", "label": "check_docker()", "file_type": "code", "source_file": "scripts/setup-db.sh", "source_location": "L25", "metadata": {"language": "bash", "kind": "bash_function"}}, {"id": "scripts_setup_db_check_postgres", "label": "check_postgres()", "file_type": "code", "source_file": "scripts/setup-db.sh", "source_location": "L39", "metadata": {"language": "bash", "kind": "bash_function"}}, {"id": "scripts_setup_db_setup_docker", "label": "setup_docker()", "file_type": "code", "source_file": "scripts/setup-db.sh", "source_location": "L50", "metadata": {"language": "bash", "kind": "bash_function"}}, {"id": "scripts_setup_db_setup_native", "label": "setup_native()", "file_type": "code", "source_file": "scripts/setup-db.sh", "source_location": "L89", "metadata": {"language": "bash", "kind": "bash_function"}}, {"id": "scripts_setup_db_update_env_file", "label": "update_env_file()", "file_type": "code", "source_file": "scripts/setup-db.sh", "source_location": "L122", "metadata": {"language": "bash", "kind": "bash_function"}}, {"id": "scripts_setup_db_run_migrations", "label": "run_migrations()", "file_type": "code", "source_file": "scripts/setup-db.sh", "source_location": "L141", "metadata": {"language": "bash", "kind": "bash_function"}}, {"id": "scripts_setup_db_run_seed", "label": "run_seed()", "file_type": "code", "source_file": "scripts/setup-db.sh", "source_location": "L148", "metadata": {"language": "bash", "kind": "bash_function"}}, {"id": "scripts_setup_db_main", "label": "main()", "file_type": "code", "source_file": "scripts/setup-db.sh", "source_location": "L154", "metadata": {"language": "bash", "kind": "bash_function"}}], "edges": [{"source": "home_ubuntu_github_qmath_scripts_setup_db_sh", "target": "home_ubuntu_github_qmath_scripts_setup_db_sh__entry", "relation": "contains", "confidence": "EXTRACTED", "source_file": "scripts/setup-db.sh", "source_location": "L1", "weight": 1.0}, {"source": "home_ubuntu_github_qmath_scripts_setup_db_sh", "target": "scripts_setup_db_check_docker", "relation": "defines", "confidence": "EXTRACTED", "source_file": "scripts/setup-db.sh", "source_location": "L25", "weight": 1.0}, {"source": "home_ubuntu_github_qmath_scripts_setup_db_sh", "target": "scripts_setup_db_check_postgres", "relation": "defines", "confidence": "EXTRACTED", "source_file": "scripts/setup-db.sh", "source_location": "L39", "weight": 1.0}, {"source": "home_ubuntu_github_qmath_scripts_setup_db_sh", "target": "scripts_setup_db_setup_docker", "relation": "defines", "confidence": "EXTRACTED", "source_file": "scripts/setup-db.sh", "source_location": "L50", "weight": 1.0}, {"source": "home_ubuntu_github_qmath_scripts_setup_db_sh", "target": "scripts_setup_db_setup_native", "relation": "defines", "confidence": "EXTRACTED", "source_file": "scripts/setup-db.sh", "source_location": "L89", "weight": 1.0}, {"source": "home_ubuntu_github_qmath_scripts_setup_db_sh", "target": "scripts_setup_db_update_env_file", "relation": "defines", "confidence": "EXTRACTED", "source_file": "scripts/setup-db.sh", "source_location": "L122", "weight": 1.0}, {"source": "home_ubuntu_github_qmath_scripts_setup_db_sh", "target": "scripts_setup_db_run_migrations", "relation": "defines", "confidence": "EXTRACTED", "source_file": "scripts/setup-db.sh", "source_location": "L141", "weight": 1.0}, {"source": "home_ubuntu_github_qmath_scripts_setup_db_sh", "target": "scripts_setup_db_run_seed", "relation": "defines", "confidence": "EXTRACTED", "source_file": "scripts/setup-db.sh", "source_location": "L148", "weight": 1.0}, {"source": "home_ubuntu_github_qmath_scripts_setup_db_sh", "target": "scripts_setup_db_main", "relation": "defines", "confidence": "EXTRACTED", "source_file": "scripts/setup-db.sh", "source_location": "L154", "weight": 1.0}, {"source": "home_ubuntu_github_qmath_scripts_setup_db_sh__entry", "target": "scripts_setup_db_main", "relation": "calls", "confidence": "EXTRACTED", "source_file": "scripts/setup-db.sh", "source_location": "L220", "weight": 1.0, "context": "call"}, {"source": "scripts_setup_db_setup_docker", "target": "scripts_setup_db_update_env_file", "relation": "calls", "confidence": "EXTRACTED", "source_file": "scripts/setup-db.sh", "source_location": "L85", "weight": 1.0, "context": "call"}, {"source": "scripts_setup_db_setup_native", "target": "scripts_setup_db_update_env_file", "relation": "calls", "confidence": "EXTRACTED", "source_file": "scripts/setup-db.sh", "source_location": "L118", "weight": 1.0, "context": "call"}, {"source": "scripts_setup_db_main", "target": "scripts_setup_db_check_docker", "relation": "calls", "confidence": "EXTRACTED", "source_file": "scripts/setup-db.sh", "source_location": "L166", "weight": 1.0, "context": "call"}, {"source": "scripts_setup_db_main", "target": "scripts_setup_db_setup_docker", "relation": "calls", "confidence": "EXTRACTED", "source_file": "scripts/setup-db.sh", "source_location": "L167", "weight": 1.0, "context": "call"}, {"source": "scripts_setup_db_main", "target": "scripts_setup_db_check_postgres", "relation": "calls", "confidence": "EXTRACTED", "source_file": "scripts/setup-db.sh", "source_location": "L175", "weight": 1.0, "context": "call"}, {"source": "scripts_setup_db_main", "target": "scripts_setup_db_setup_native", "relation": "calls", "confidence": "EXTRACTED", "source_file": "scripts/setup-db.sh", "source_location": "L176", "weight": 1.0, "context": "call"}, {"source": "scripts_setup_db_main", "target": "scripts_setup_db_run_migrations", "relation": "calls", "confidence": "EXTRACTED", "source_file": "scripts/setup-db.sh", "source_location": "L195", "weight": 1.0, "context": "call"}, {"source": "scripts_setup_db_main", "target": "scripts_setup_db_run_seed", "relation": "calls", "confidence": "EXTRACTED", "source_file": "scripts/setup-db.sh", "source_location": "L203", "weight": 1.0, "context": "call"}]}